<?xml version="1.0" encoding="UTF-8"?>
<nicovideo_thumb_response status="ok"><thumb><video_id>sm44892130</video_id><title>【Minecraft 1.20.1】しにがみとまほー #07 【VOICEVOX実況】</title><description>プレイがぐちゃぐちゃで、ぐちゃぐちゃの上に重ねていくから余計進行もぐちゃぐちゃに。心の乱れがプレイにしっかり反映されてますね。更新頻度が落ち気味ですが、恐らく今後は1週間に2回できればよさそうかなぁという感じです。Minecraft 1.20.1 / 魔術MODメインの自前環境で遊んでいく動画です。導入MOD一覧 : https://note.com/hexqua/n/n19f5441e961a前 : sm44875320次 : sm44894673VOICEVOX : 冥鳴ひまりVOICEVOX : 春日部つむぎBGM : MusMusBGM : BGMerSE : OtoLogic (CC BY 4.0)</description><thumbnail_url>https://nicovideo.cdn.nimg.jp/thumbnails/44892130/44892130.87310656</thumbnail_url><first_retrieve>2025-04-19T13:31:03+09:00</first_retrieve><length>16:21</length><movie_type>mp4</movie_type><size_high>1</size_high><size_low>1</size_low><view_counter>278</view_counter><comment_num>35</comment_num><mylist_counter>0</mylist_counter><last_res_body>おつ うぽつ 画像も貼らずにス... そりゃ鉄棒で殴ら... おつー ソームではボタニ... バニラでも歪んだ... 　ワァオー はえー 拠点崩壊とかね そういう時...</last_res_body><watch_url>https://www.nicovideo.jp/watch/sm44892130</watch_url><thumb_type>video</thumb_type><embeddable>1</embeddable><no_live_play>0</no_live_play><tags domain="jp"><tag lock="1">Minecraft</tag><tag lock="1">voicevox実況プレイ</tag><tag lock="1">VOICEVOX</tag><tag lock="1">冥鳴ひまり</tag><tag lock="1">春日部つむぎ</tag><tag lock="1">冥鳴ひまり実況プレイ</tag></tags><genre>ゲーム</genre><user_id>699062</user_id><user_nickname>Aquid</user_nickname><user_icon_url>https://secure-dcdn.cdn.nimg.jp/nicoaccount/usericon/69/699062.jpg?1730726496</user_icon_url></thumb></nicovideo_thumb_response>
