<?xml version="1.0" encoding="UTF-8"?>
<nicovideo_thumb_response status="ok"><thumb><video_id>sm44789065</video_id><title>意識が突然なくなった。ワクチン血栓か？今後交通事故急増する。その兆候がでている</title><description>αシクロデキストリンhttps://amzn.to/4huhuiN黒ニンニクhttps://amzn.to/4iFGKncスイマグhttps://amzn.to/4huqh4n菊芋パウダーhttps://amzn.to/41FJ1Id発芽玄米　玄氣https://amzn.to/4inhjqL土鍋かまどさんhttps://amzn.to/4bIILgcヨモギ茶https://amzn.to/4iVgWn0パクチーパウダーhttps://amzn.to/3R7vPH7海の精　梅干しhttps://amzn.to/4hxfaHL秋ウコンhttps://amzn.to/3WZlhNNひまし油https://amzn.to/4hn1QGEたんぽぽ茶無農薬https://amzn.to/3WegYgZばんのう酵母くんhttps://amzn.to/3DP9oQfクローブhttps://amzn.to/3OPGLsH刀豆粉末https://amzn.to/4fmwjD8梅肉エキスhttps://amzn.to/3ZzoRzM　　　刀豆茶https://amzn.to/3VdvHIyムクナ豆https://amzn.to/494rGfuスギナ粉https://amzn.to/40nAnPC日向樟脳https://amzn.to/3NSf9So黒ひまし油https://amzn.to/3Nf6VU7松葉茶https://amzn.to/3XBzxeXなた豆茶https://amzn.to/3K6ebjSゼオライトhttps://amzn.to/46l95Ja麻炭パウダーhttps://amzn.to/3s9ojT33年梅干しhttps://amzn.to/3r3i7vi黒ムクナ豆https://amzn.to/3JFVvqOニーム茶https://amzn.to/3Nil1Vjそば蜂蜜https://amzn.to/45qDdDMホウ砂https://amzn.to/43GoHpb</description><thumbnail_url>https://nicovideo.cdn.nimg.jp/thumbnails/44789065/44789065.43320007</thumbnail_url><first_retrieve>2025-03-21T14:00:00+09:00</first_retrieve><length>14:47</length><movie_type>mp4</movie_type><size_high>1</size_high><size_low>1</size_low><view_counter>4729</view_counter><comment_num>36</comment_num><mylist_counter>1</mylist_counter><last_res_body>FDA、mRNAワクチン... https://t.me/moxy... こわ ホワイトグロット ホワイトグロット ホワイトグロット...</last_res_body><watch_url>https://www.nicovideo.jp/watch/sm44789065</watch_url><thumb_type>video</thumb_type><embeddable>1</embeddable><no_live_play>0</no_live_play><tags domain="jp"><tag lock="1">交通事故</tag><tag lock="1">ワクチン血栓症</tag><tag lock="1">ワクチンと交通事故</tag><tag lock="1">ワクチン事故</tag><tag lock="1">ワクチンの危険性</tag><tag lock="1">ワクチン危険</tag><tag>プリウスミサイル</tag><tag>森羅万象はワクのせい</tag></tags><genre>社会・政治・時事</genre><user_id>2504611</user_id><user_nickname>日本神話古事記朗読カイフ</user_nickname><user_icon_url>https://secure-dcdn.cdn.nimg.jp/nicoaccount/usericon/250/2504611.jpg?1702548901</user_icon_url></thumb></nicovideo_thumb_response>
