<?xml version="1.0" encoding="UTF-8"?>
<nicovideo_thumb_response status="ok"><thumb><video_id>sm45013501</video_id><title>Elin遠距離のみ縛り！ガンナーIAが巡る世界3</title><description>見慣れた風景を目にした時、私の心は踊り狂った。前：sm44767945次：sm45070015</description><thumbnail_url>https://nicovideo.cdn.nimg.jp/thumbnails/45013501/45013501.10016541</thumbnail_url><first_retrieve>2025-05-23T19:32:04+09:00</first_retrieve><length>6:55</length><movie_type>mp4</movie_type><size_high>1</size_high><size_low>1</size_low><view_counter>302</view_counter><comment_num>8</comment_num><mylist_counter>1</mylist_counter><last_res_body>グウェンちゃんモ... 草とか木じゃない... 人工種族MODが入っ... 人工種族MOD入って... おつ あかりちゃーーー... wwwww うぽつ</last_res_body><watch_url>https://www.nicovideo.jp/watch/sm45013501</watch_url><thumb_type>video</thumb_type><embeddable>1</embeddable><no_live_play>0</no_live_play><tags domain="jp"><tag lock="1">ゲーム</tag><tag lock="1">IA実況プレイ</tag><tag lock="1">紲星あかり実況プレイ</tag><tag lock="1">VOICEROID実況プレイ</tag><tag lock="1">elin</tag><tag>ローグライク</tag></tags><genre>ゲーム</genre><user_id>92527283</user_id><user_nickname>羊羹</user_nickname><user_icon_url>https://secure-dcdn.cdn.nimg.jp/nicoaccount/usericon/9252/92527283.jpg?1648907626</user_icon_url></thumb></nicovideo_thumb_response>
