<?xml version="1.0" encoding="UTF-8"?>
<nicovideo_thumb_response status="ok"><thumb><video_id>sm45322655</video_id><title>【Ratopia】お雪んちゅとラットピア その２【VOICEVOX実況プレイ】</title><description>ゆるゆりしてるので初投稿です。お雪ちゃんかわいいやったー！されてください。🌱お借りしたBGM音楽：フリー音楽素材 H/MIX GALLERYhttp://www.hmix.net/フリーBGM・音楽素材MusMushttps://musmus.main.jp/©2025 Pokémon. ©1995-2025 Nintendo/Creatures Inc./GAME FREAK inc.これは「Pokémon Game Sound Library」の利用規約に同意し作成されたコンテンツです。https://soundlibrary.pokemon.co.jp/VOICEVOX:WhiteCULhttps://www.whitecul.com/VOICEVOX:春日部つむぎhttps://tsumugi-official.studio.site/topVOICEVOX:四国めたんVOICEVOX:ずんだもんhttps://zunko.jp/</description><thumbnail_url>https://nicovideo.cdn.nimg.jp/thumbnails/45322655/45322655.20513376</thumbnail_url><first_retrieve>2025-08-22T20:28:03+09:00</first_retrieve><length>9:56</length><movie_type>mp4</movie_type><size_high>1</size_high><size_low>1</size_low><view_counter>28</view_counter><comment_num>1</comment_num><mylist_counter>1</mylist_counter><last_res_body>うぽつ</last_res_body><watch_url>https://www.nicovideo.jp/watch/sm45322655</watch_url><thumb_type>video</thumb_type><embeddable>1</embeddable><no_live_play>0</no_live_play><tags domain="jp"><tag lock="1">ゲーム</tag><tag lock="1">Ratopia</tag><tag lock="1">voicevox実況プレイ</tag><tag lock="1">whitecul実況プレイ</tag><tag lock="1">春日部つむぎ実況プレイ</tag><tag lock="1">百合</tag></tags><genre>ゲーム</genre><user_id>141292749</user_id><user_nickname>二葉ベス</user_nickname><user_icon_url>https://secure-dcdn.cdn.nimg.jp/nicoaccount/usericon/14129/141292749.jpg?1755432347</user_icon_url></thumb></nicovideo_thumb_response>
