<?xml version="1.0" encoding="UTF-8"?>
<nicovideo_thumb_response status="ok"><thumb><video_id>sm44907024</video_id><title>【ワンダーホルンに】デイジー・ベル【歌ってもらった】</title><description>泣く子も黙るNTT-ATが開発した、知る人ぞ知る全く流行しなかった歌声合成ソフト「ワンダーホルン」に、ボカロ課題曲ともいえるデイジー・ベルを歌ってもらいました。かなり調声が面倒で、ちょっとやってらんなかったので素材の味を生かした無調声となっております。体験版を使用したので、ヒヨコの声のようなスクラッチ音が入っていますが仕様です。入院中に病院から支給されたモノラルイヤホンで聞きながら作ったので、いろいろご容赦ください。Music: HARRY DACREVOCAL: Wonder Horn F1DB by NTT-ATMIDI Edit: うづ（キョロ）P</description><thumbnail_url>https://nicovideo.cdn.nimg.jp/thumbnails/44907024/44907024.38473557</thumbnail_url><first_retrieve>2025-04-23T19:31:03+09:00</first_retrieve><length>1:31</length><movie_type>mp4</movie_type><size_high>1</size_high><size_low>1</size_low><view_counter>50</view_counter><comment_num>5</comment_num><mylist_counter>0</mylist_counter><last_res_body>半音段階的にズレ... 体験版では４４０...</last_res_body><watch_url>https://www.nicovideo.jp/watch/sm44907024</watch_url><thumb_type>video</thumb_type><embeddable>1</embeddable><no_live_play>0</no_live_play><tags domain="jp"><tag lock="1">VOCALOID</tag><tag lock="1">ワンダーホルン</tag><tag lock="1">カバー曲</tag></tags><genre>音楽・サウンド</genre><user_id>48671382</user_id><user_nickname>うづ（キョロ）P</user_nickname><user_icon_url>https://secure-dcdn.cdn.nimg.jp/nicoaccount/usericon/4867/48671382.jpg?1670335457</user_icon_url></thumb></nicovideo_thumb_response>
