<?xml version="1.0" encoding="UTF-8"?>
<nicovideo_thumb_response status="ok"><thumb><video_id>sm45059554</video_id><title>【CPUvsCPU】[恋姫夢想]格ゲーで総当たり戦(07)第26～30試合</title><description>この動画は「真・恋姫夢想 乙女対戦★三国志演義」(Windows版)のCPU同士を総当たり戦で戦わせて、最強キャラを決める動画です。最初の動画：sm44957438　前回の動画：sm45049875　次の動画：　★ゲーム設定★対戦形式：CPUvsCPU、CPU難易度：８(最大)、ラウンド数：５(３Ｒ先取で勝利)、時間無制限　★ルール★全10人による総当たり戦で、最終的に勝ちラウンド数の最も多いキャラが優勝。勝ちラウンド数が同じ場合は、負けラウンド数が少ない方が上位となる。（例：２-３で試合に負けた時、勝ちＲ数：２、負けＲ数：３）　★今回の試合（全45試合中）★第26試合　張飛(+諸葛亮) vs 甘寧(+呂蒙)第27試合　孫権(+呂蒙) vs 夏侯淵(+程昱)第28試合　夏侯惇(+荀彧) vs 曹操(+程昱)第29試合　趙雲(+鳳統) vs 孫尚香(+呂蒙)第30試合　呂布(+陳宮) vs 関羽(+諸葛亮)第30試合はステージ演出でPC負荷が大きいためか、動きがやや重いです。本当は続編の『恋姫演武』で試してみたかった企画ですが、そちらではCPU観戦が出来ないようなので断念。この10人の中で誰が最強の座を掴むのか!?</description><thumbnail_url>https://nicovideo.cdn.nimg.jp/thumbnails/45059554/45059554.24709302</thumbnail_url><first_retrieve>2025-06-06T11:00:00+09:00</first_retrieve><length>21:04</length><movie_type>mp4</movie_type><size_high>1</size_high><size_low>1</size_low><view_counter>5</view_counter><comment_num>0</comment_num><mylist_counter>1</mylist_counter><last_res_body/><watch_url>https://www.nicovideo.jp/watch/sm45059554</watch_url><thumb_type>video</thumb_type><embeddable>1</embeddable><no_live_play>0</no_live_play><tags domain="jp"><tag lock="1">格闘ゲーム</tag><tag lock="1">真・恋姫†夢想〜乙女対戦★三国志演義〜</tag><tag lock="1">恋姫†無双</tag></tags><genre>ゲーム</genre><user_id>13952716</user_id><user_nickname>shinkura</user_nickname><user_icon_url>https://secure-dcdn.cdn.nimg.jp/nicoaccount/usericon/1395/13952716.jpg?1665226023</user_icon_url></thumb></nicovideo_thumb_response>
