<?xml version="1.0" encoding="UTF-8"?>
<nicovideo_thumb_response status="ok"><thumb><video_id>sm45266483</video_id><title>【ミストトレインガールズ】キャラシナリオ [SS][枕に詰めた寂寥]ウォータールー</title><description>はいどうも、くりあです。DMMGAMES ミストトレインガールズ 霧の世界の車窓から のアプリ版キャラシナリオ を動画に収録しました。公式：https://mist-train-girls.com/[SS][枕に詰めた寂寥]ウォータールーStory1 甘いお菓子のようにStory2 子供たちが消えた町Story3 悪戯はほどほどにStory4 神隠しの真相Story5 温かな抱擁遠征でとある町に立ち寄っていた車掌とトレインナイトたちだったのだがその中で、ウォータールーがお菓子に釣られて誘拐されそうになっていた……どうやらこの町では、小さい子供たちが神隠しにあっているらしい。神隠し…つまり、誘拐事件だ。まさかその噂を聞いた直後に、身内が被害に遭いそうになっているとは……[A][墓守の少女]ウォータールー → sm42745310[S][いつでもいっしょ]ウォータールー → sm40993719[S][遊び盛りの甘えん坊]ウォータールー → sm45247056[SS][ドキドキ遊園地デート☆]ウォータールー → sm43334569</description><thumbnail_url>https://nicovideo.cdn.nimg.jp/thumbnails/45266483/45266483.83319612</thumbnail_url><first_retrieve>2025-08-08T00:00:08+09:00</first_retrieve><length>15:24</length><movie_type>mp4</movie_type><size_high>1</size_high><size_low>1</size_low><view_counter>10</view_counter><comment_num>0</comment_num><mylist_counter>0</mylist_counter><last_res_body/><watch_url>https://www.nicovideo.jp/watch/sm45266483</watch_url><thumb_type>video</thumb_type><embeddable>1</embeddable><no_live_play>0</no_live_play><tags domain="jp"><tag lock="1">DMM</tag><tag lock="1">DMMGAMES</tag><tag lock="1">ミストトレインガールズ</tag><tag lock="1">ミストレ</tag><tag lock="1">ウォータールー</tag><tag lock="1">ウォータールー(ミストレ)</tag></tags><genre>ゲーム</genre><user_id>30765823</user_id><user_nickname>くりあ２号</user_nickname><user_icon_url>https://secure-dcdn.cdn.nimg.jp/nicoaccount/usericon/3076/30765823.jpg?1354794399</user_icon_url></thumb></nicovideo_thumb_response>
