<?xml version="1.0" encoding="UTF-8"?>
<nicovideo_thumb_response status="ok"><thumb><video_id>sm44985356</video_id><title>全術禁止サラマンシングでリベサガプレイ Part4【VOICEPEAK実況】【ロマンシングサガ2 リベンジオブザセブン】【ロマサガ2R】</title><description>世界旅行編とはなんだったのか。制作まにあわず、次回は2週間後になります…牛乳先生です。今回はダンターグに挑みます！ベアがスゴイカツヤクしてくれます！ベアすごい！ところでボス戦が長すぎて、掛け合いネタ考えるのが辛いんですが！■縛り内容1.難易度サラマンシング2.1周目データを引き継いで始めること3.ウィルガード引き継ぎ禁止4.全術禁止(武器経由も禁止)5.「インペリアル」陣形のみ使用可6.ベア系を必ず採用する＋パリイと防御のみ使用可(アイテム・連携攻撃OK)7.ラスボス以外での武器破壊技の禁止8.故意のバグ利用禁止(Ver1.0.0)←前 sm44949839　次 sm45033206(5/31予定) →←2周目最初 sm44882142 マイリス mylist/77975737牛乳先生の他のシリーズ！user/5335518/series撮影日:24/11/04～05声: VOICEPEAK:京町セイカ、CeVIO AI さとうささら© SQUARE ENIX</description><thumbnail_url>https://nicovideo.cdn.nimg.jp/thumbnails/44985356/44985356.580275</thumbnail_url><first_retrieve>2025-05-17T18:00:00+09:00</first_retrieve><length>13:51</length><movie_type>mp4</movie_type><size_high>1</size_high><size_low>1</size_low><view_counter>481</view_counter><comment_num>29</comment_num><mylist_counter>1</mylist_counter><last_res_body>合わせて115%回避... 退位するだけじゃ.... 世界が広がってな... お前が今回のMVPだ！ 1周目だとあんなに... さらっとルドン送... さらっと皇帝変わ... なんで連携使わな... 多...</last_res_body><watch_url>https://www.nicovideo.jp/watch/sm44985356</watch_url><thumb_type>video</thumb_type><embeddable>1</embeddable><no_live_play>0</no_live_play><tags domain="jp"><tag lock="1">voicepeak実況プレイ</tag><tag lock="1">縛りプレイ</tag><tag lock="1">京町セイカ</tag><tag lock="1">さとうささら</tag><tag lock="1">ロマンシングサガ2_リベンジオブザセブン</tag><tag lock="1">ロマサガ2R</tag><tag lock="1">全術縛り</tag><tag lock="1">難易度ロマンシング</tag><tag lock="1">リベサガ</tag></tags><genre>ゲーム</genre><user_id>5335518</user_id><user_nickname>牛乳先生</user_nickname><user_icon_url>https://secure-dcdn.cdn.nimg.jp/nicoaccount/usericon/533/5335518.jpg?1387705495</user_icon_url></thumb></nicovideo_thumb_response>
