<?xml version="1.0" encoding="UTF-8"?>
<nicovideo_thumb_response status="ok"><thumb><video_id>sm45128798</video_id><title>【ゆっくり解説】魔神転生 Part.12/12</title><description>シナリオ５６～５９前→sm45040103・えんまくだん・トラエスト禁止・稼ぎマップ周回禁止(イベント除く)・全ステージクリア(例の橋も)以上の緩めの縛りでLightエンディング目指す。レトロフリークでプレイしています。Ⓒ1994 ATLUS</description><thumbnail_url>https://nicovideo.cdn.nimg.jp/thumbnails/45128798/45128798.48891630</thumbnail_url><first_retrieve>2025-06-27T17:58:03+09:00</first_retrieve><length>20:34</length><movie_type>mp4</movie_type><size_high>1</size_high><size_low>1</size_low><view_counter>3422</view_counter><comment_num>239</comment_num><mylist_counter>13</mylist_counter><last_res_body>完走おつかれさま... 完走お疲れさまで... お疲れ様でした!あ... よかった！！ 良いゲームでした！！ なおシュヴァルツ... このゲームに限ら... 中古で買って前オ...</last_res_body><watch_url>https://www.nicovideo.jp/watch/sm45128798</watch_url><thumb_type>video</thumb_type><embeddable>1</embeddable><no_live_play>0</no_live_play><tags domain="jp"><tag lock="1">ゆっくり実況プレイ</tag><tag lock="1">レトロゲーム</tag><tag lock="1">スーパーファミコン</tag><tag lock="1">魔神転生</tag><tag lock="1">SFC</tag><tag lock="1">睡眠導入動画</tag><tag>biimシステム</tag><tag>ゆっくり実況プレイ最終回リンク</tag></tags><genre>ゲーム</genre><user_id>78038173</user_id><user_nickname>ARIWA</user_nickname><user_icon_url>https://secure-dcdn.cdn.nimg.jp/nicoaccount/usericon/7803/78038173.jpg?1533234286</user_icon_url></thumb></nicovideo_thumb_response>
