<?xml version="1.0" encoding="UTF-8"?>
<nicovideo_thumb_response status="ok"><thumb><video_id>sm45133877</video_id><title>日本の大学　ハーバード追放スパイ　受け入れの危機！　2025／6／12　</title><description>米トランプ大統領が追放した留学生を、なんと日本の大学が拾うことに・・しかも無償で？？</description><thumbnail_url>https://nicovideo.cdn.nimg.jp/thumbnails/45133877/45133877.93374675</thumbnail_url><first_retrieve>2025-06-29T18:24:04+09:00</first_retrieve><length>8:22</length><movie_type>mp4</movie_type><size_high>1</size_high><size_low>1</size_low><view_counter>7</view_counter><comment_num>0</comment_num><mylist_counter>0</mylist_counter><last_res_body/><watch_url>https://www.nicovideo.jp/watch/sm45133877</watch_url><thumb_type>video</thumb_type><embeddable>1</embeddable><no_live_play>0</no_live_play><tags domain="jp"><tag lock="1">ハーバード大学</tag><tag lock="1">外国人留学生</tag><tag lock="1">留学生を無償で受入れ</tag><tag lock="1">東京大学</tag><tag lock="1">大阪大学</tag><tag lock="1">九州大学</tag></tags><genre>社会・政治・時事</genre><user_id>117094720</user_id><user_nickname>てつや</user_nickname><user_icon_url>https://secure-dcdn.cdn.nimg.jp/nicoaccount/usericon/11709/117094720.jpg?1613544480</user_icon_url></thumb></nicovideo_thumb_response>
