<?xml version="1.0" encoding="UTF-8"?>
<nicovideo_thumb_response status="ok"><thumb><video_id>sm44774760</video_id><title>東方カトリー々夢影澤 ~ food or Male Calpis</title><description>たんおめ</description><thumbnail_url>https://nicovideo.cdn.nimg.jp/thumbnails/44774760/44774760.87208159</thumbnail_url><first_retrieve>2025-03-17T23:47:03+09:00</first_retrieve><length>1:38</length><movie_type>mp4</movie_type><size_high>1</size_high><size_low>1</size_low><view_counter>191</view_counter><comment_num>3</comment_num><mylist_counter>1</mylist_counter><last_res_body>ファンですよ ざわっちチャージ... 寒そう</last_res_body><watch_url>https://www.nicovideo.jp/watch/sm44774760</watch_url><thumb_type>video</thumb_type><embeddable>1</embeddable><no_live_play>0</no_live_play><tags domain="jp"><tag lock="1">おとざわっち</tag><tag lock="1">音MAD</tag><tag lock="1">東方カトリー々夢影澤</tag><tag lock="1">妖々夢_～_Snow_or_Cherry_Petal</tag><tag lock="1">東方坐倭致</tag><tag lock="1">ざわっち誕生祭'25</tag><tag lock="1">ざわっち</tag><tag>マスペクト</tag></tags><genre>その他</genre><user_id>122866622</user_id><user_nickname>エラエラ</user_nickname><user_icon_url>https://secure-dcdn.cdn.nimg.jp/nicoaccount/usericon/12286/122866622.jpg?1655603367</user_icon_url></thumb></nicovideo_thumb_response>
