<?xml version="1.0" encoding="UTF-8"?>
<nicovideo_thumb_response status="ok"><thumb><video_id>sm44791226</video_id><title>R-TYPE FINAL3 EVOLVED R-11Aのみでスコアタ1ミスクリア　後半</title><description>R-TYPE FINAL3 EVOLVEDのスコアアタックモードにて、R-11Aフューチャー・ワールドのみでクリアしました。（1ミス有り）コースエディットは、X3.0→6.2→4.0→Y3.0→5.1→Y6.0→7.2となっております。後半は5.1からになります。ハイスコア更新を目的としているので、ボス戦などでスコア稼ぎがあり、単調な部分もありますがご了承下さい。投稿者コメントでプレイのポイントを書いてみました。（お邪魔でしたらコメント一時非表示にして下さい）また一部稼ぎの為同じような画面が続く場合もありますのでご了承下さい。前半sm44770430投稿や動画編集など初めてだらけなので至らない部分もあるかもしれませんが、楽しんでいただければ幸いです。</description><thumbnail_url>https://nicovideo.cdn.nimg.jp/thumbnails/44791226/44791226.37304775</thumbnail_url><first_retrieve>2025-03-21T19:22:04+09:00</first_retrieve><length>28:41</length><movie_type>mp4</movie_type><size_high>1</size_high><size_low>1</size_low><view_counter>63</view_counter><comment_num>2</comment_num><mylist_counter>1</mylist_counter><last_res_body>おつ うぽつ</last_res_body><watch_url>https://www.nicovideo.jp/watch/sm44791226</watch_url><thumb_type>video</thumb_type><embeddable>1</embeddable><no_live_play>0</no_live_play><tags domain="jp"><tag lock="1">ゲーム</tag><tag lock="1">R-TYPE</tag><tag lock="1">R-TYPE_FINAL3_EVOLVED</tag><tag lock="1">R-TYPE_FINAL3</tag><tag lock="1">R-TYPE_FINAL2</tag><tag lock="1">R-11A</tag></tags><genre>ゲーム</genre><user_id>4947032</user_id><user_nickname>zeoce</user_nickname><user_icon_url>https://secure-dcdn.cdn.nimg.jp/nicoaccount/usericon/494/4947032.jpg?1358235063</user_icon_url></thumb></nicovideo_thumb_response>
