<?xml version="1.0" encoding="UTF-8"?>
<nicovideo_thumb_response status="ok"><thumb><video_id>sm45259096</video_id><title>斬日 - 至高、極陽、天空の化身『エーグル』第一形態BGM</title><description>個人用</description><thumbnail_url>https://nicovideo.cdn.nimg.jp/thumbnails/45259096/45259096.92488462</thumbnail_url><first_retrieve>2025-08-05T17:59:03+09:00</first_retrieve><length>1:42</length><movie_type>mp4</movie_type><size_high>1</size_high><size_low>1</size_low><view_counter>30</view_counter><comment_num>0</comment_num><mylist_counter>0</mylist_counter><last_res_body/><watch_url>https://www.nicovideo.jp/watch/sm45259096</watch_url><thumb_type>video</thumb_type><embeddable>1</embeddable><no_live_play>0</no_live_play><tags domain="jp"><tag lock="1">崩壊スターレイル</tag><tag lock="1">ゲームBGM</tag><tag lock="1">エーグル</tag></tags><genre>音楽・サウンド</genre><user_id>91306737</user_id><user_nickname>アンクル</user_nickname><user_icon_url>https://secure-dcdn.cdn.nimg.jp/nicoaccount/usericon/defaults/blank.jpg</user_icon_url></thumb></nicovideo_thumb_response>
