<?xml version="1.0" encoding="UTF-8"?>
<nicovideo_thumb_response status="ok"><thumb><video_id>sm45007821</video_id><title>【アサルトリリィ Last Bullet】美味しい時間</title><description>はいどうも、くりあです。スマートフォンアプリ「アサルトリリィ Last Bullet（ラスバレ）」を動画に収録しました。公式：https://assaultlily-pj.com/イベント期間：2025/05/21～2025/05/31美味しい時間今日は、どうやらお好み焼きを楽しく作っているらしいローエングリンの3人通りがかった梨璃や閑を誘うが、2人はこれから用があるようだ。だが、楓は紗癒、広夢、雪陽のお好み焼きづくりに興味津々……？どうやら、梨璃のために美味しいお好み焼きの作り方をマスターしたいようだ。というわけで、楓も含めてお好み焼きをどんどん作っていく。何かと優秀な楓は、すぐさまお好み焼きの作り方もマスターしたようだがどうも納得いく形に作り上げられないようだ。何かが足りない…そう感じる楓に、紗癒さんはひとつアドバイスをしてくれて……？</description><thumbnail_url>https://nicovideo.cdn.nimg.jp/thumbnails/45007821/45007821.11464619</thumbnail_url><first_retrieve>2025-05-21T22:52:03+09:00</first_retrieve><length>10:41</length><movie_type>mp4</movie_type><size_high>1</size_high><size_low>1</size_low><view_counter>32</view_counter><comment_num>5</comment_num><mylist_counter>0</mylist_counter><last_res_body>伊勢海老？鈴夢ち... このメイド服は衣... でもマグロ解体は... 真「お好み焼きな... しずりりで予定……</last_res_body><watch_url>https://www.nicovideo.jp/watch/sm45007821</watch_url><thumb_type>video</thumb_type><embeddable>1</embeddable><no_live_play>0</no_live_play><tags domain="jp"><tag lock="1">アサルトリリィ</tag><tag lock="1">ラスバレ</tag><tag lock="1">アサルトリリィ_lastbullet</tag></tags><genre>ゲーム</genre><user_id>30765823</user_id><user_nickname>くりあ２号</user_nickname><user_icon_url>https://secure-dcdn.cdn.nimg.jp/nicoaccount/usericon/3076/30765823.jpg?1354794399</user_icon_url></thumb></nicovideo_thumb_response>
