<?xml version="1.0" encoding="UTF-8"?>
<nicovideo_thumb_response status="ok"><thumb><video_id>sm45309305</video_id><title>日ハムが勝つたびに気持ちよく勝ちたい音街ウナのマリオカート8DX　Season2　67勝目</title><description>レトルト動画2日目series/511286 ←元ネタ様のザンギおいしいさんのファイターズが負けないと試合ができない栄冠ナイン</description><thumbnail_url>https://nicovideo.cdn.nimg.jp/thumbnails/45309305/45309305.55176891</thumbnail_url><first_retrieve>2025-08-20T01:13:04+09:00</first_retrieve><length>3:00</length><movie_type>mp4</movie_type><size_high>1</size_high><size_low>1</size_low><view_counter>21</view_counter><comment_num>1</comment_num><mylist_counter>0</mylist_counter><last_res_body>ｗ</last_res_body><watch_url>https://www.nicovideo.jp/watch/sm45309305</watch_url><thumb_type>video</thumb_type><embeddable>1</embeddable><no_live_play>0</no_live_play><tags domain="jp"><tag lock="1">VOICEROID実況プレイ</tag><tag lock="1">マリオカート8DX</tag><tag lock="1">音街ウナ実況プレイ</tag><tag lock="1">日ハムファン</tag><tag lock="1">東北きりたん実況プレイ</tag></tags><genre>ゲーム</genre><user_id>26419941</user_id><user_nickname>ν酸菌</user_nickname><user_icon_url>https://secure-dcdn.cdn.nimg.jp/nicoaccount/usericon/2641/26419941.jpg?1739086603</user_icon_url></thumb></nicovideo_thumb_response>
