<?xml version="1.0" encoding="UTF-8"?>
<nicovideo_thumb_response status="ok"><thumb><video_id>sm45246894</video_id><title>【ASMROID】小夜ちゃんはあなたに夜更かししてほしくない</title><description>2024年の12月9日に投稿した小夜ちゃんの続きです!小夜ちゃんの声が聴きたかったので半年振りに続きを作りました!……半年前???前回➝https://www.nicovideo.jp/watch/sm44408718?ref=garage_share_other youtube https://www.youtube.com/@sugarsalt_0125X(旧Twitter) https://x.com/sugar_salt0125クレジット表記声VOICEVOX：小夜/SAYO立ち絵https://seiga.nicovideo.jp/seiga/im11097974画像・音声素材ニコニコモンズ様、効果音ラボ様、みりんちえ様、MOTOKN様、どこでも使えるASMR素材集 VOL.4耳かき様</description><thumbnail_url>https://nicovideo.cdn.nimg.jp/thumbnails/45246894/45246894.44396004</thumbnail_url><first_retrieve>2025-08-01T22:42:04+09:00</first_retrieve><length>34:34</length><movie_type>mp4</movie_type><size_high>1</size_high><size_low>1</size_low><view_counter>900</view_counter><comment_num>9</comment_num><mylist_counter>32</mylist_counter><last_res_body>しょうがないにゃあ 小夜ちゃんや！ うぽつ うぽっつ小夜ちゃ... うぽつです うぽつ うぽつですー！！ うぽつです！投稿... うぽつです！</last_res_body><watch_url>https://www.nicovideo.jp/watch/sm45246894</watch_url><thumb_type>video</thumb_type><embeddable>1</embeddable><no_live_play>0</no_live_play><tags domain="jp"><tag lock="1">小夜/sayo</tag><tag lock="1">VOICEVOX</tag><tag lock="1">ASMROID</tag><tag lock="1">ASMR</tag></tags><genre>エンターテイメント</genre><user_id>137304396</user_id><user_nickname>しゅがると</user_nickname><user_icon_url>https://secure-dcdn.cdn.nimg.jp/nicoaccount/usericon/13730/137304396.jpg?1736576573</user_icon_url></thumb></nicovideo_thumb_response>
