<?xml version="1.0" encoding="UTF-8"?>
<nicovideo_thumb_response status="ok"><thumb><video_id>sm45051793</video_id><title>【大学生が歌う】身バレリサイタル 【天羽しろっぷ・オリジナル曲】</title><description>身バレしたい人手をあげて～？ﾟ*｡，｡*ﾟ*｡，｡*ﾟ*｡，｡*ﾟ*｡，｡*ﾟ*｡，｡*ﾟ*｡，｡*ﾟ*｡，｡*ﾟ*｡，｡*ﾟ*｡，｡*ﾟ=== 歌詞 ===人間には皆誰しもが一つや二つや三つ 秘密があるもんだただ一人だけを除いてそうさ、私は無敵状態身バレしたい人手を挙げて身バレしたい人こっちを見てもう手遅れですから♪もうなんも気にしない^a^もうなんも気にしない^a^知らぬ間にマジな情報流出してなぜなぜなぜ？もうなんも気にしない^a^もうなんも気にしない^a^この際もう全部全部吹っ切れて個人情報を暴露します身長　重さ　バストサイズ年齢　性別　好きなタイプ性癖　特技　アレの数今日も一日 はいしんだ^a^ﾟ*｡，｡*ﾟ*｡，｡*ﾟ*｡，｡*ﾟ*｡，｡*ﾟ*｡，｡*ﾟ*｡，｡*ﾟ*｡，｡*ﾟ*｡，｡*ﾟ*｡，｡*ﾟ●歌：天羽しろっぷ●作曲・作詞・編曲・MIX : Ponchi♪様https://x.com/ponchi_pop●animation・illustration : I様https://x.com/MiiverseI●サムネ：𝗕𝗔𝗤様https://x.com/B_A_9_X●エンコード：折乃りづ様https://x.com/riz_xxxxx●Shortダンス振付：わた（春）様https://x.com/wata0w0</description><thumbnail_url>https://nicovideo.cdn.nimg.jp/thumbnails/45051793/45051793.5755746</thumbnail_url><first_retrieve>2025-06-04T20:00:00+09:00</first_retrieve><length>1:10</length><movie_type>mp4</movie_type><size_high>1</size_high><size_low>1</size_low><view_counter>750</view_counter><comment_num>6</comment_num><mylist_counter>2</mylist_counter><last_res_body>祝ニコニコニュー... うぽつ ドラえもん「死ん... 88888888 うぽつ うぽつ</last_res_body><watch_url>https://www.nicovideo.jp/watch/sm45051793</watch_url><thumb_type>video</thumb_type><embeddable>1</embeddable><no_live_play>0</no_live_play><tags domain="jp"><tag>天羽しろっぷ</tag><tag>身バレリサイタル</tag><tag>Ponchi♪</tag><tag>オリジナル曲</tag><tag>ニコニコインディーズ</tag></tags><genre>音楽・サウンド</genre><user_id>118353809</user_id><user_nickname>天羽しろっぷ</user_nickname><user_icon_url>https://secure-dcdn.cdn.nimg.jp/nicoaccount/usericon/11835/118353809.jpg?1674144980</user_icon_url></thumb></nicovideo_thumb_response>
