<?xml version="1.0" encoding="UTF-8"?>
<nicovideo_thumb_response status="ok"><thumb><video_id>sm44993288</video_id><title>【ホラー】漂流の果てに辿り着いた島で待つ恐怖とは？【A.I.VOICE2 結月ゆかり】【Seaport Man】</title><description>画質が味になる結月ゆかりさんが茜ちゃんおすすめのゲームで遊ぶ動画です。今回のゲーム：SEAPORT MANhttps://store.steampowered.com/app/3515290/SEAPORT_MAN/</description><thumbnail_url>https://nicovideo.cdn.nimg.jp/thumbnails/44993288/44993288.96806383</thumbnail_url><first_retrieve>2025-06-13T17:00:00+09:00</first_retrieve><length>3:39</length><movie_type>mp4</movie_type><size_high>1</size_high><size_low>1</size_low><view_counter>1486</view_counter><comment_num>163</comment_num><mylist_counter>1</mylist_counter><last_res_body>食べ物がないか探... メアリー・セレスト号 これはホラゲーじ... なんちゅう脆いバ... 落下中の鳥？ うぽつ ドラム缶に詰めら... 龍撃槍ありそう（... しまっ...</last_res_body><watch_url>https://www.nicovideo.jp/watch/sm44993288</watch_url><thumb_type>video</thumb_type><embeddable>1</embeddable><no_live_play>0</no_live_play><tags domain="jp"><tag lock="1">VOICEROID実況プレイ</tag><tag lock="1">ソフトウェアトーク実況プレイ</tag><tag lock="1">VOICEROID実況プレイ単発リンク</tag><tag lock="1">結月ゆかり実況プレイ</tag><tag lock="1">実況プレイ動画</tag><tag lock="1">結月ゆかり</tag><tag>Seaport_man</tag><tag>a.i.voice実況プレイ</tag><tag>自作立ち絵</tag><tag>ホラーVOICEROID実況</tag></tags><genre>ゲーム</genre><user_id>119941711</user_id><user_nickname>めがさら</user_nickname><user_icon_url>https://secure-dcdn.cdn.nimg.jp/nicoaccount/usericon/11994/119941711.jpg?1739257990</user_icon_url></thumb></nicovideo_thumb_response>
