<?xml version="1.0" encoding="UTF-8"?>
<nicovideo_thumb_response status="ok"><thumb><video_id>sm44936580</video_id><title>画面を70％隠して死にげーやってみた【Lies of P】【VOICEROID実況】</title><description>ご視聴ありがとうございます。 チャンネル登録高評価お願いします まほ。さんという方企画を勝手に参考にさせていただきました まほ。さんのチャンネル：UCVrANr5fv70lwt23frPjdqw ◆立ち絵 作者: かれい 様 ◆音声 VOICEROID＋ 東北きりたん◆BGM 浦鉾さちこ 様 Fancy_Pop</description><thumbnail_url>https://nicovideo.cdn.nimg.jp/thumbnails/44936580/44936580.35746742</thumbnail_url><first_retrieve>2025-05-01T21:19:03+09:00</first_retrieve><length>19:43</length><movie_type>mp4</movie_type><size_high>1</size_high><size_low>1</size_low><view_counter>32</view_counter><comment_num>2</comment_num><mylist_counter>0</mylist_counter><last_res_body>なんもわからんｗ 主人公見えないの草</last_res_body><watch_url>https://www.nicovideo.jp/watch/sm44936580</watch_url><thumb_type>video</thumb_type><embeddable>1</embeddable><no_live_play>0</no_live_play><tags domain="jp"><tag lock="1">VOICEROID実況プレイ</tag><tag lock="1">東北きりたん実況プレイ</tag><tag lock="1">初投稿</tag><tag lock="1">縛りプレイ</tag><tag lock="1">lies_of_p</tag><tag lock="1">死にゲー</tag></tags><genre>ゲーム</genre><user_id>139895921</user_id><user_nickname>ちちんぷいぷい</user_nickname><user_icon_url>https://secure-dcdn.cdn.nimg.jp/nicoaccount/usericon/13989/139895921.jpg?1746099312</user_icon_url></thumb></nicovideo_thumb_response>
