<?xml version="1.0" encoding="UTF-8"?>
<nicovideo_thumb_response status="ok"><thumb><video_id>sm44970362</video_id><title>【刀剣乱舞偽実況】伯仲が海底遺跡で冒険者生活・18</title><description>みかんに思考を侵蝕されつつある写しとマッピングオーラを取得しつつある本歌が嫌な予感を感じつつ白い森へ足を踏み入れる話。B16F～B17F前半vs　キリン今までのシリーズ・作品にコメントやいいね、広告等ありがとうございました。進捗・裏設定話・連絡用タイッツー/Xアカウント：syocyu5hon世界樹の迷宮Ⅰ・Ⅱ・Ⅲ　HD REMASTER公式サイトhttps://sq-atlus.jp/sq123/Steam版公式https://store.steampowered.com/app/1868170/__HD_REMASTER/©ATLUS ©SEGA世界樹の迷宮Ⅲシリーズ：series/491807刀剣乱舞偽実況単発＆part1まとめ：mylist/73792011</description><thumbnail_url>https://nicovideo.cdn.nimg.jp/thumbnails/44970362/44970362.75497736</thumbnail_url><first_retrieve>2025-05-10T22:49:04+09:00</first_retrieve><length>21:42</length><movie_type>mp4</movie_type><size_high>1</size_high><size_low>1</size_low><view_counter>1693</view_counter><comment_num>222</comment_num><mylist_counter>6</mylist_counter><last_res_body>←自分でPT組んだら... 1層から5層に昇進... このギミックとリ... 一発突...</last_res_body><watch_url>https://www.nicovideo.jp/watch/sm44970362</watch_url><thumb_type>video</thumb_type><embeddable>1</embeddable><no_live_play>0</no_live_play><tags domain="jp"><tag lock="1">刀剣乱舞偽実況</tag><tag lock="1">山姥切国広(刀剣乱舞)</tag><tag lock="1">山姥切長義(刀剣乱舞)</tag><tag lock="1">世界樹の迷宮Ⅲ</tag><tag>伯仲コンビ</tag><tag>イカの鍵</tag><tag>壮大な兄弟喧嘩</tag><tag>フラグ立ての匠</tag><tag>何故みかんに突っ込むのか</tag></tags><genre>ゲーム</genre><user_id>1242878</user_id><user_nickname>焼酎</user_nickname><user_icon_url>https://secure-dcdn.cdn.nimg.jp/nicoaccount/usericon/124/1242878.jpg?1655742237</user_icon_url></thumb></nicovideo_thumb_response>
