<?xml version="1.0" encoding="UTF-8"?>
<nicovideo_thumb_response status="ok"><thumb><video_id>sm45154247</video_id><title>目隠しされて期待に膨らんだ アソコは決して触ってくれないご主人様　囁き</title><description>え〇え〇なシチュボ投稿してるみゅーみゅーです！最近はオ〇サポ音声を積極的に投稿してます。X(旧Twitter)にて情報をお伝えしています。フォローよろしくお願いいたします！https://twitter.com/fantia_myumyuまみむめめ様のフリー台本を使用いたしました。</description><thumbnail_url>https://nicovideo.cdn.nimg.jp/thumbnails/45154247/45154247.26533343</thumbnail_url><first_retrieve>2025-07-05T02:04:04+09:00</first_retrieve><length>7:10</length><movie_type>mp4</movie_type><size_high>1</size_high><size_low>1</size_low><view_counter>114</view_counter><comment_num>0</comment_num><mylist_counter>1</mylist_counter><last_res_body/><watch_url>https://www.nicovideo.jp/watch/sm45154247</watch_url><thumb_type>video</thumb_type><embeddable>1</embeddable><no_live_play>0</no_live_play><tags domain="jp"><tag lock="1">R-18</tag><tag lock="1">囁き</tag><tag lock="1">例のアレ</tag><tag lock="1">ASMR</tag><tag lock="1">言葉責め</tag><tag lock="1">同人音声</tag></tags><genre>例のソレ</genre><user_id>95185517</user_id><user_nickname>みゅーみゅー</user_nickname><user_icon_url>https://secure-dcdn.cdn.nimg.jp/nicoaccount/usericon/9518/95185517.jpg?1700059852</user_icon_url></thumb></nicovideo_thumb_response>
