<?xml version="1.0" encoding="UTF-8"?>
<nicovideo_thumb_response status="ok"><thumb><video_id>sm44769532</video_id><title>購入</title><description>VOICEVOX：四国めたんBGM：MusMus&amp;gt;&amp;gt; タクソンに新規参入するならこっち買った方がいいんでしかね？まずはNEUTRINOとNEUTRINO調声支援ツールで始めるのがいいと思いまっす。無料だし、AIの力でMIDIそのままでもいい感じに歌ってくれるので。すでに音楽経験やソフトに歌わせた経験があって（四国めたんに歌わせる覚悟）キメてるんなら、（買って）くれ（てもいい）よ…</description><thumbnail_url>https://nicovideo.cdn.nimg.jp/thumbnails/44769532/44769532.86550199</thumbnail_url><first_retrieve>2025-03-16T19:01:04+09:00</first_retrieve><length>1:34</length><movie_type>mp4</movie_type><size_high>1</size_high><size_low>1</size_low><view_counter>31877</view_counter><comment_num>646</comment_num><mylist_counter>16</mylist_counter><last_res_body>シコシコシコシコ... ここ日本語の難し... 深いね やったぁ！ 巻き込むな (なんで替え歌拓也... 初心者ですよー！(... こんなものが愛で... おお おお...</last_res_body><watch_url>https://www.nicovideo.jp/watch/sm44769532</watch_url><thumb_type>video</thumb_type><embeddable>1</embeddable><no_live_play>0</no_live_play><tags domain="jp"><tag lock="1">日記</tag><tag>業務連絡淫夢</tag><tag>四国めたん</tag><tag>ステロイドマーケティング</tag><tag>自分を買う</tag><tag>テロ等準備罪</tag><tag>恋文</tag><tag>文通淫夢</tag><tag>四国めたん(淫夢)</tag><tag>投稿者☆</tag><tag>自分をボイロだと思い込んでいる精神異常者</tag></tags><genre>その他</genre><user_id>122016054</user_id><user_nickname>タラバ記念日</user_nickname><user_icon_url>https://secure-dcdn.cdn.nimg.jp/nicoaccount/usericon/12201/122016054.jpg?1730564367</user_icon_url></thumb></nicovideo_thumb_response>
