<?xml version="1.0" encoding="UTF-8"?>
<nicovideo_thumb_response status="ok"><thumb><video_id>sm45084363</video_id><title>【ゆめ2っき】夢孤島奥地RTA 23:22:83 解説【ver.0.125gパッチ5】</title><description>ver.0.125gパッチ5を使用計測開始:{はじめて}を押した瞬間計測終了:奥地に移動する道に触れた瞬間 今回は去年の12月にアップしたRTA動画をVOICEVOXで解説してみました。解説と言えるのかどうか分からないですが、楽しんでいただければ光栄です。VOICEVOX:四国めたん四国めたん立ち絵:たおたお様コモズン様、bobobo様、二人は幸せな接吻をして終了様、ToM様、ニコニ広告ありがとうございます。</description><thumbnail_url>https://nicovideo.cdn.nimg.jp/thumbnails/45084363/45084363.58825611</thumbnail_url><first_retrieve>2025-06-13T20:10:04+09:00</first_retrieve><length>25:10</length><movie_type>mp4</movie_type><size_high>1</size_high><size_low>1</size_low><view_counter>764</view_counter><comment_num>62</comment_num><mylist_counter>5</mylist_counter><last_res_body>何のための機能な... しち (走ら)ないです えぇ… ｗｗｗ f ここ背景いいな 解説しろよｗ 他走者のために更... 雑談多すぎるｗ 知らなかった このRTA初見だなぁ うぽつーー すみませんでした バネ取るなら夜眼...</last_res_body><watch_url>https://www.nicovideo.jp/watch/sm45084363</watch_url><thumb_type>video</thumb_type><embeddable>1</embeddable><no_live_play>0</no_live_play><tags domain="jp"><tag lock="1">ゲーム</tag><tag lock="1">ゆめ２っき</tag><tag lock="1">ゆめにっき派生</tag><tag lock="1">RTA</tag><tag lock="1">biimシステム</tag><tag lock="1">biim兄貴リスペクト</tag></tags><genre>ゲーム</genre><user_id>124266621</user_id><user_nickname>Ilovemoneyegirl</user_nickname><user_icon_url>https://secure-dcdn.cdn.nimg.jp/nicoaccount/usericon/12426/124266621.jpg?1733758414</user_icon_url></thumb></nicovideo_thumb_response>
