<?xml version="1.0" encoding="UTF-8"?>
<nicovideo_thumb_response status="ok"><thumb><video_id>sm44865325</video_id><title>食の軍師 WhiteCUL明　頂上決戦！　日高屋の戦い！</title><description>第一部完◇いいねには今回の撮影の裏話が描かれている……？X（Twitter）:https://x.com/gehaSyaki使用ソフト：VOICEVOX:WhiteCUL VOICEVOX:ずんだもん VOICEVOX:青山龍星使用立ち絵：moiky氏 坂本アヒル氏 Who inside氏使用BGM：飛翔鉄塔 かずち氏 中華ラーメン 田中芳典氏 Senjin -戦神- GT-K氏Chinatown Folk_Chinese Shenxian Wuxia2 むつき醒氏効果音ラボ Music:MoGura 神との決別【開闢のラグナロク_Ver 2.0】</description><thumbnail_url>https://nicovideo.cdn.nimg.jp/thumbnails/44865325/44865325.38502932</thumbnail_url><first_retrieve>2025-04-11T17:00:00+09:00</first_retrieve><length>19:02</length><movie_type>mp4</movie_type><size_high>1</size_high><size_low>1</size_low><view_counter>60040</view_counter><comment_num>3781</comment_num><mylist_counter>101</mylist_counter><last_res_body>今朝もやったんか... あ、油が跳ねて綺... こいつに突撃させ... 元ネタの子亡くな... ◆この窪みは一体…？ うおおお うわーー え？ ちょっと日高屋い... 天才 →なにｗ 王道 キンクリいて草 あ...</last_res_body><watch_url>https://www.nicovideo.jp/watch/sm44865325</watch_url><thumb_type>video</thumb_type><embeddable>1</embeddable><no_live_play>0</no_live_play><tags domain="jp"><tag lock="1">VOICEROID劇場</tag><tag lock="1">ずんだもん</tag><tag lock="1">WhiteCUL</tag><tag lock="1">食の軍師</tag><tag lock="1">四国めたん</tag><tag lock="1">日高屋</tag><tag lock="1">VOICEROIDグルメ</tag><tag>中華料理</tag><tag>食の軍師WhiteCUL明</tag></tags><genre>エンターテイメント</genre><user_id>417032</user_id><user_nickname>しゃきん太</user_nickname><user_icon_url>https://secure-dcdn.cdn.nimg.jp/nicoaccount/usericon/41/417032.jpg?1582035786</user_icon_url></thumb></nicovideo_thumb_response>
