<?xml version="1.0" encoding="UTF-8"?>
<nicovideo_thumb_response status="ok"><thumb><video_id>sm44982221</video_id><title>【Elin】漆黒聖騎士めたんちゃん08</title><description>Elinやっていきます。次→sm45026079パート１→sm44626095・導入modEnchantValueDisplay切石厚板絶対解体KK Unlimited StethoscopeKK Whip Selector土地獲得時にフィート選択VOICEVOX:四国めたんVOICEVOX:ずんだもん広告ありがとうございました！ゆのさん　†漆黒の堕天使しょこ†さん　青の森さん　日本たぬき党さん</description><thumbnail_url>https://nicovideo.cdn.nimg.jp/thumbnails/44982221/44982221.91145044</thumbnail_url><first_retrieve>2025-05-14T20:00:05+09:00</first_retrieve><length>25:04</length><movie_type>mp4</movie_type><size_high>1</size_high><size_low>1</size_low><view_counter>459</view_counter><comment_num>9</comment_num><mylist_counter>0</mylist_counter><last_res_body>ジョジョネタとか... 開幕パルミアベイ... 謎過ぎる リアル四国にも欲... 普通ならブラシで... うぽつ うぽつ うぽーつ</last_res_body><watch_url>https://www.nicovideo.jp/watch/sm44982221</watch_url><thumb_type>video</thumb_type><embeddable>1</embeddable><no_live_play>0</no_live_play><tags domain="jp"><tag lock="1">elin</tag><tag lock="1">voicevox実況プレイ</tag><tag lock="1">四国めたん</tag><tag lock="1">ずんだもん</tag><tag>ローグライク</tag></tags><genre>ゲーム</genre><user_id>15524554</user_id><user_nickname>青い悪魔予備軍</user_nickname><user_icon_url>https://secure-dcdn.cdn.nimg.jp/nicoaccount/usericon/1552/15524554.jpg?1664068188</user_icon_url></thumb></nicovideo_thumb_response>
