<?xml version="1.0" encoding="UTF-8"?>
<nicovideo_thumb_response status="ok"><thumb><video_id>sm45323313</video_id><title>【オリジナル曲】からんころん / 可不【ボカロ】</title><description>からんころんと落ちていく どこまで続く？■ボカコレ2025夏TOP100ランキング参加曲です。『The VOCALOID Collection（ボカコレ）』はボカロ文化をきっかけに生まれたインターネット等で活動するクリエイターやユーザー、企業などボカロに関わる全ての方が参加できるボカロ文化の祭典です。https://vocaloid-collection.jp/からんころん/可不Illustration usahikoMovie GLSからんころんと落ちていく 留まること知らずからんころんと落ちていく どこまで続く？からんころんと落ちていく 私の形の何かどんどんと速くなる まだまだ続くあの日 ぱりんと割れた窓ガラスもう全部限界でぱらんぱらんと雨が降る何かを間違えたまぁ しゃーないな 傍から見たら悪化だろうがじゃあ どうしろと？ 信じてたけど救われなかったあぁ むしろ逆に？ 中途半端で見下されてたあの時よりもずっとましずっとまし！呑んで呑んで あるだけ飲んで嘘も無理も飲み込んで吐いて吐いて 全部を吐いて受け入れられる場所もなく売れるものから手放してなるべく高値で売り出してちゃりんちゃりんと数字が見えるからんころんの音がする-amen-からんころんと落ちていく 私だった何かどんどんと速くなる まだまだ続く私ちゃらんぽらんの人生でこっちの地獄が良く見えてまんまと嵌まってて 何かを間違えたからんころん 跳ねるように軽くからんころん 破滅に進むからんころん 幸せそうにからんころん 上はもう見えない半端者には見えやしない下の下まで落ちた私は完全勝利呼んで呼んで 名前を呼んで私がここにいることを認めて止めて褒めて染めて何も知りたくないから『運命の人に出会って幸せに暮らしましたとさ』あらん限りの祝福を！からんからんと音がするなんっちゅー人生や全部全部分かってる散々な人生ややんややんやうるさいわからんなんでなんで どうしてなんで 私はここにいるのでしょう？待って待って 今更なんで 後悔は捨てたはずなのにやること全てが裏に出て 幸せのために間違えてからんころんと落ちていく 留まることも知らずからんころんと落ちていく どこまで続く？</description><thumbnail_url>https://nicovideo.cdn.nimg.jp/thumbnails/45323313/45323313.63476775</thumbnail_url><first_retrieve>2025-08-23T00:00:00+09:00</first_retrieve><length>3:49</length><movie_type>mp4</movie_type><size_high>1</size_high><size_low>1</size_low><view_counter>67</view_counter><comment_num>5</comment_num><mylist_counter>5</mylist_counter><last_res_body>めちゃ可愛い 8888888888 声と曲が完全合致... ここすき 好き～</last_res_body><watch_url>https://www.nicovideo.jp/watch/sm45323313</watch_url><thumb_type>video</thumb_type><embeddable>1</embeddable><no_live_play>0</no_live_play><tags domain="jp"><tag lock="1">ボカコレ2025夏TOP100ランキング参加曲</tag><tag lock="1">可不</tag><tag lock="1">可不オリジナル曲</tag><tag lock="1">可不はじめました</tag><tag lock="1">CeVIOオリジナル曲</tag></tags><genre>音楽・サウンド</genre><user_id>121360032</user_id><user_nickname>crescendless・おりー</user_nickname><user_icon_url>https://secure-dcdn.cdn.nimg.jp/nicoaccount/usericon/12136/121360032.jpg?1634196396</user_icon_url></thumb></nicovideo_thumb_response>
