<?xml version="1.0" encoding="UTF-8"?>
<nicovideo_thumb_response status="ok"><thumb><video_id>sm45010423</video_id><title>神経細胞は雨雲レーダーの夢を見る / 小春六花</title><description>シンセで音色を作れるようになったので、水中で泡が発生しているような音を作って間奏とエンディングに入れてみました。コーラスの声がきれいだと思います。</description><thumbnail_url>https://nicovideo.cdn.nimg.jp/thumbnails/45010423/45010423.14437620</thumbnail_url><first_retrieve>2025-05-22T20:48:03+09:00</first_retrieve><length>4:22</length><movie_type>mp4</movie_type><size_high>1</size_high><size_low>1</size_low><view_counter>120</view_counter><comment_num>5</comment_num><mylist_counter>2</mylist_counter><last_res_body>8888888888888888 六花良い声！ 古き良き歌謡の気... タイトルおもしろ うぽつです</last_res_body><watch_url>https://www.nicovideo.jp/watch/sm45010423</watch_url><thumb_type>video</thumb_type><embeddable>1</embeddable><no_live_play>0</no_live_play><tags domain="jp"><tag lock="1">SynthesizerV</tag><tag lock="1">synthesizervオリジナル曲</tag><tag lock="1">小春六花</tag><tag lock="1">小春六花オリジナル曲</tag><tag lock="1">音楽</tag><tag>VOCALOID</tag><tag>vocaloid新曲リンク</tag><tag>synthesizerv新曲リンク</tag></tags><genre>音楽・サウンド</genre><user_id>16412173</user_id><user_nickname>きんめろん</user_nickname><user_icon_url>https://secure-dcdn.cdn.nimg.jp/nicoaccount/usericon/1641/16412173.jpg?1584801015</user_icon_url></thumb></nicovideo_thumb_response>
