<?xml version="1.0" encoding="UTF-8"?>
<nicovideo_thumb_response status="ok"><thumb><video_id>sm45165373</video_id><title>バーでゲロ吐いてうんこ漏らすと叱られるから</title><description>東方便堕流</description><thumbnail_url>https://nicovideo.cdn.nimg.jp/thumbnails/45165373/45165373.7968349</thumbnail_url><first_retrieve>2025-07-08T02:39:03+09:00</first_retrieve><length>0:36</length><movie_type>mp4</movie_type><size_high>1</size_high><size_low>1</size_low><view_counter>1191</view_counter><comment_num>29</comment_num><mylist_counter>2</mylist_counter><last_res_body>大草原 👴オ"エ"ェ"ッ！！... 👴オ"エ"ェ"ッ！！... 👴オ"エ"ェ"ッ！！... 👴オ"エ"ェ"ッ！！... ・・・ ある日 私は「やってはい... MAD作者さんはもち...</last_res_body><watch_url>https://www.nicovideo.jp/watch/sm45165373</watch_url><thumb_type>video</thumb_type><embeddable>1</embeddable><no_live_play>0</no_live_play><tags domain="jp"><tag lock="1">カツドンチャンネル</tag><tag lock="1">カツドンmad</tag><tag lock="1">稲田姫様に叱られるから</tag><tag lock="1">音MAD</tag><tag lock="1">東方皿屋敷</tag><tag lock="1">原曲不使用</tag></tags><genre>その他</genre><user_id>52209256</user_id><user_nickname>ハゲの特権</user_nickname><user_icon_url>https://secure-dcdn.cdn.nimg.jp/nicoaccount/usericon/5220/52209256.jpg?1747755070</user_icon_url></thumb></nicovideo_thumb_response>
