<?xml version="1.0" encoding="UTF-8"?>
<nicovideo_thumb_response status="ok"><thumb><video_id>sm45018306</video_id><title>【紲星あかり】新作エロゲを紹介する【2025年7月発売予定】</title><description>2025年7月に発売を予定している作品を紹介する動画です。動画冒頭でも書いておりますが、Getchu.comの発売予定一覧の中から独断と偏見で選んでおります。他にもいくつか発売予定の作品もございますので、興味がございましたらブランドサイトでご確認いただければと思います。◆あかりちゃん動画まとめ　mylist/66002835前回：sm44913515次回：sm45124271(7/1_6:00投稿予定)◆ お借りした素材フリーBGM・音楽素材MusMus（http://musmus.main.jp/）</description><thumbnail_url>https://nicovideo.cdn.nimg.jp/thumbnails/45018306/45018306.66654984</thumbnail_url><first_retrieve>2025-06-01T06:00:00+09:00</first_retrieve><length>13:29</length><movie_type>mp4</movie_type><size_high>1</size_high><size_low>1</size_low><view_counter>11169</view_counter><comment_num>691</comment_num><mylist_counter>41</mylist_counter><last_res_body>どうしてそうなった UR主人公 これは凄い あー 完結してくれてク... これ終わったのか ママとの親子丼な... あの、アレなアレか ノーマルで後半ま... 左下の...</last_res_body><watch_url>https://www.nicovideo.jp/watch/sm45018306</watch_url><thumb_type>video</thumb_type><embeddable>1</embeddable><no_live_play>0</no_live_play><tags domain="jp"><tag lock="1">ニコニコ動画講座</tag><tag lock="1">エロゲ</tag><tag lock="1">ゲーム</tag><tag lock="1">紲星あかり</tag><tag lock="1">VOICEROID解説</tag><tag lock="1">マグナム(動画投稿者)</tag><tag>エロゲ紹介</tag><tag>紹介動画</tag><tag>修羅の国(エロゲ業界)</tag><tag>廃村少女</tag><tag>アンラベル・トリガー</tag></tags><genre>解説・講座</genre><user_id>1201830</user_id><user_nickname>マグナム</user_nickname><user_icon_url>https://secure-dcdn.cdn.nimg.jp/nicoaccount/usericon/120/1201830.jpg?1562427738</user_icon_url></thumb></nicovideo_thumb_response>
