<?xml version="1.0" encoding="UTF-8"?>
<nicovideo_thumb_response status="ok"><thumb><video_id>sm45196411</video_id><title>国道158号線(√ BEAST)＿feat.重音テト</title><description>生を迂回して獣に至るバイパスを求めて。-------------------------------------めっちゃ詩を書いた。ボイスピ強すぎ。『国道158号線』Vocal：重音テト(UTAU＆VOICEPEAK)Bass：ると&amp;lt;@ruto_nintai&amp;gt;others :よめいよめいのマイリスト：mylist/71988234よめいのYouTube：https://www.youtube.com/channel/UCUNLV31E2i5MjX0pctDosRgよめいのTwitter：https://twitter.com/Yoake_Tonbo-------------------------------------広告など本当にありがとうございます。</description><thumbnail_url>https://nicovideo.cdn.nimg.jp/thumbnails/45196411/45196411.46677075</thumbnail_url><first_retrieve>2025-07-17T20:00:11+09:00</first_retrieve><length>6:10</length><movie_type>mp4</movie_type><size_high>1</size_high><size_low>1</size_low><view_counter>154</view_counter><comment_num>10</comment_num><mylist_counter>10</mylist_counter><last_res_body>GJ!! すごかった… よめいさん曲も絵... サビすき ボイスピテトさん... GJ おつ 88888888888888888... うぽつです 888888888888</last_res_body><watch_url>https://www.nicovideo.jp/watch/sm45196411</watch_url><thumb_type>video</thumb_type><embeddable>1</embeddable><no_live_play>0</no_live_play><tags domain="jp"><tag lock="1">重音テト</tag><tag lock="1">重音テトVP</tag><tag lock="1">utau</tag><tag lock="1">voicepeak</tag><tag lock="1">vocaloid</tag><tag>UTAUオリジナル曲</tag><tag>テトオリジナル曲</tag><tag>vocaloid新曲リンク</tag></tags><genre>音楽・サウンド</genre><user_id>121342256</user_id><user_nickname>よめい</user_nickname><user_icon_url>https://secure-dcdn.cdn.nimg.jp/nicoaccount/usericon/12134/121342256.jpg?1634045454</user_icon_url></thumb></nicovideo_thumb_response>
