<?xml version="1.0" encoding="UTF-8"?>
<nicovideo_thumb_response status="ok"><thumb><video_id>sm45084563</video_id><title>QVC 20250603 「全農食品から来た福ちゃんの息子とイチャイチャする石橋」</title><description>全編→sm45078715関西弁がちょこちょこ出る橋本さんかわいい息子というのは噓です</description><thumbnail_url>https://nicovideo.cdn.nimg.jp/thumbnails/45084563/45084563.61048614</thumbnail_url><first_retrieve>2025-06-13T21:22:03+09:00</first_retrieve><length>6:30</length><movie_type>mp4</movie_type><size_high>1</size_high><size_low>1</size_low><view_counter>165</view_counter><comment_num>4</comment_num><mylist_counter>4</mylist_counter><last_res_body>どれだよ いっしーとはっし... QVC本編リンクタグ... 味　　障</last_res_body><watch_url>https://www.nicovideo.jp/watch/sm45084563</watch_url><thumb_type>video</thumb_type><embeddable>1</embeddable><no_live_play>0</no_live_play><tags domain="jp"><tag lock="1">QVC</tag><tag lock="1">橋本康平</tag><tag lock="1">かわいいは正義</tag><tag lock="1">QVC石橋</tag><tag lock="1">飯テロ</tag><tag lock="1">デブ専ホイホイ</tag><tag>QVC本編リンク</tag><tag>例のアレ</tag><tag>JA橋本</tag><tag>料理</tag><tag>エンターテイメント</tag></tags><genre>エンターテイメント</genre><user_id>140320306</user_id><user_nickname>大福ちゃん</user_nickname><user_icon_url>https://secure-dcdn.cdn.nimg.jp/nicoaccount/usericon/14032/140320306.jpg?1748743193</user_icon_url></thumb></nicovideo_thumb_response>
