<?xml version="1.0" encoding="UTF-8"?>
<nicovideo_thumb_response status="ok"><thumb><video_id>sm45161182</video_id><title>さとうとしお - フレフレ！マイハート feat. 音街ウナ SV</title><description>はじめまして、さとうとしおです。  歌: 音街ウナSV 作詞&amp;amp;作曲&amp;amp;イラスト&amp;amp;動画: さとうとしお → https://twitter.com/satoutoshio_11サブスク等 → https://linkco.re/EMg9H7m2オフボーカル → 配布予定</description><thumbnail_url>https://nicovideo.cdn.nimg.jp/thumbnails/45161182/45161182.90162374</thumbnail_url><first_retrieve>2025-07-07T12:27:04+09:00</first_retrieve><length>3:55</length><movie_type>mp4</movie_type><size_high>1</size_high><size_low>1</size_low><view_counter>131</view_counter><comment_num>3</comment_num><mylist_counter>1</mylist_counter><last_res_body>理屈無しの楽しさ... 8888888888 うぽつ</last_res_body><watch_url>https://www.nicovideo.jp/watch/sm45161182</watch_url><thumb_type>video</thumb_type><embeddable>1</embeddable><no_live_play>0</no_live_play><tags domain="jp"><tag lock="1">VOCALOID</tag><tag lock="1">音街ウナ</tag><tag lock="1">vocaloidオリジナル曲</tag><tag lock="1">SynthesizerV</tag><tag lock="1">VOCALOID処女作</tag><tag lock="1">オリジナル曲</tag></tags><genre>音楽・サウンド</genre><user_id>140779462</user_id><user_nickname>さとうとしお</user_nickname><user_icon_url>https://secure-dcdn.cdn.nimg.jp/nicoaccount/usericon/14077/140779462.jpg?1751898280</user_icon_url></thumb></nicovideo_thumb_response>
