<?xml version="1.0" encoding="UTF-8"?>
<nicovideo_thumb_response status="ok"><thumb><video_id>sm44763032</video_id><title>「夢花火 / IA」 まふまふ様　【歌ってみた】　まくら</title><description>◾️本家様 / sm21489609◾️まふまふ様歌唱ver / sm21676184◾️お借りした音源 / https://piapro.jp/t/PSiP※映像・サムネイルは、自作のものを使用しております。まくらと申します!まふまふ様の「夢花火 / IA」を歌ってみました。技術も実力もないので、大目に見てくださると幸いです!また、私の投稿動画に関して、ネット上、ニコニコ動画上のマナーに反することがあれば教えていただけると幸いです。早急に訂正いたします。歌唱 イラスト MIX / まくら</description><thumbnail_url>https://nicovideo.cdn.nimg.jp/thumbnails/44763032/44763032.92205197</thumbnail_url><first_retrieve>2025-03-15T13:06:03+09:00</first_retrieve><length>4:26</length><movie_type>mp4</movie_type><size_high>1</size_high><size_low>1</size_low><view_counter>18</view_counter><comment_num>0</comment_num><mylist_counter>0</mylist_counter><last_res_body/><watch_url>https://www.nicovideo.jp/watch/sm44763032</watch_url><thumb_type>video</thumb_type><embeddable>1</embeddable><no_live_play>0</no_live_play><tags domain="jp"><tag lock="1">音楽</tag><tag lock="1">歌ってみた</tag><tag lock="1">まふまふ</tag><tag lock="1">夢花火</tag><tag lock="1">IA</tag><tag lock="1">初投稿(歌い手)</tag></tags><genre>音楽・サウンド</genre><user_id>139126218</user_id><user_nickname>まくら</user_nickname><user_icon_url>https://secure-dcdn.cdn.nimg.jp/nicoaccount/usericon/13912/139126218.jpg?1742029170</user_icon_url></thumb></nicovideo_thumb_response>
