<?xml version="1.0" encoding="UTF-8"?>
<nicovideo_thumb_response status="ok"><thumb><video_id>sm44854563</video_id><title>【MHシリーズ解説実況】モンハンディクショナリー：ダブルクロス　ドスファンゴ＆ドスギアノス[モンハンシリーズ実況の始まり]【ゆっくり実況】</title><description>ニコニコ動画での投稿、始めました。ぜひ見ていってね！！！！！！！！！ゆっくり実況を盛り上げるイカれたメンバー 〇さや（男） ・撮影、編集、美術等担当。 ・字幕色：紫 ・チャンネル主（俺）で、とてつもなくガサツ ・初モンハンはMHP2の古参ハンター ・廃人ゲーマー、最近原神とペルソナ3にハマっている 〇りん（女） ・解説役 ・字幕色：水色 ・ツッコミ役、とにかくディノバルド大好き ・初モンハンはMHXX ・とにかく尻尾を切断したがっている 〇てぃー（女） ・ゲーマー枠 ・字幕色：灰色 ・ボケ役でもツッコミ役でも、唯一のボクっ娘 ・初モンハンはMHW ・さや、りんと比べてやや大人しめ---------- Youtubeでも動画投稿してます！ [https://www.youtube.com/channel/UCG8-DFtuhwn-xvG5-ILGPmQ] ---------- Twitter:@Cyah_Gamer[https://twitter.com/Cyah_Gamer]</description><thumbnail_url>https://nicovideo.cdn.nimg.jp/thumbnails/44854563/44854563.94806388</thumbnail_url><first_retrieve>2025-04-07T21:22:05+09:00</first_retrieve><length>4:35</length><movie_type>mp4</movie_type><size_high>1</size_high><size_low>1</size_low><view_counter>138</view_counter><comment_num>1</comment_num><mylist_counter>0</mylist_counter><last_res_body>面白かった</last_res_body><watch_url>https://www.nicovideo.jp/watch/sm44854563</watch_url><thumb_type>video</thumb_type><embeddable>1</embeddable><no_live_play>0</no_live_play><tags domain="jp"><tag lock="1">MHXX</tag><tag lock="1">モンハンダブルクロス</tag><tag lock="1">モンハンXX</tag><tag lock="1">ゆっくり</tag><tag lock="1">ゆっくり実況</tag></tags><genre>ゲーム</genre><user_id>48005507</user_id><user_nickname>ニコニコのCyA（さや）</user_nickname><user_icon_url>https://secure-dcdn.cdn.nimg.jp/nicoaccount/usericon/4800/48005507.jpg?1744027004</user_icon_url></thumb></nicovideo_thumb_response>
