<?xml version="1.0" encoding="UTF-8"?>
<nicovideo_thumb_response status="ok"><thumb><video_id>sm44914324</video_id><title>【音だけ車載祭】社会のボトムズが物価高にむせながらお米を買いに行く話</title><description>ゆかり「音だけ車載祭だと？俺はガンダムで行く！（大嘘）」投稿主の表現スキル的に音だけでの表現では・映像なしで誰にでもイメージしやすいもは何か？・告知動画や補足説明によると車やバイクでなくともいいらしいつまりは「一般人の見識」でも解像度が高い装甲騎兵ボトムズが最適なんだぜ！みたいになっちゃいましたｗもうパクリもいいところなんですが、まあぶっちゃけてウド編の手乗りフィアナのデート回の絵をゆかあかで作りたかっただけです既読スルーがデフォの滅多にアクションがない投稿主のXhttps://x.com/Tanaka_Ken003 (@Tanaka_Ken003) / Xマイリスト　mylist/65335421前　sm44892486　次　sm44968424</description><thumbnail_url>https://nicovideo.cdn.nimg.jp/thumbnails/44914324/44914324.82299470</thumbnail_url><first_retrieve>2025-04-25T22:33:03+09:00</first_retrieve><length>5:26</length><movie_type>mp4</movie_type><size_high>1</size_high><size_low>1</size_low><view_counter>1551</view_counter><comment_num>143</comment_num><mylist_counter>5</mylist_counter><last_res_body>ターンピックが冴... むせる うぽうぽ うぽつです〜 中古車売ってるホ... おっそうだな なるほど む せ る 巨乳ハンター思い... 待って！パワーコ... うぽつです〜 おつ！ 思い切りやれ　転...</last_res_body><watch_url>https://www.nicovideo.jp/watch/sm44914324</watch_url><thumb_type>video</thumb_type><embeddable>1</embeddable><no_live_play>0</no_live_play><tags domain="jp"><tag lock="1">車載動画</tag><tag lock="1">紲星あかり</tag><tag lock="1">VOICEROID旅行</tag><tag lock="1">結月ゆかり</tag><tag lock="1">音だけ車載祭</tag><tag lock="1">VOICEROID車載</tag><tag>最低野郎</tag><tag>装甲騎兵ボトムズ</tag><tag>一般人の認識</tag></tags><genre>旅行・アウトドア</genre><user_id>88958284</user_id><user_nickname>田中　健</user_nickname><user_icon_url>https://secure-dcdn.cdn.nimg.jp/nicoaccount/usericon/8895/88958284.jpg?1691802662</user_icon_url></thumb></nicovideo_thumb_response>
