<?xml version="1.0" encoding="UTF-8"?>
<nicovideo_thumb_response status="ok"><thumb><video_id>sm44960654</video_id><title>八幡謙百パーセント</title><description>色々リスペクトシテます</description><thumbnail_url>https://nicovideo.cdn.nimg.jp/thumbnails/44960654/44960654.49592468</thumbnail_url><first_retrieve>2025-05-08T02:04:04+09:00</first_retrieve><length>1:16</length><movie_type>mp4</movie_type><size_high>1</size_high><size_low>1</size_low><view_counter>3617</view_counter><comment_num>14</comment_num><mylist_counter>93</mylist_counter><last_res_body>デカキンへの悪口？ ヌルヌルルーレッ... 音MAD作者全員これ なにこれw 普通にね こんな会話噛み合... 八幡テキストああ... よすぎる ｗｗｗｗｗｗｗｗ... 金だろ普通に♪ 迫真お肉部好き うおっまぶしっ それ...</last_res_body><watch_url>https://www.nicovideo.jp/watch/sm44960654</watch_url><thumb_type>video</thumb_type><embeddable>1</embeddable><no_live_play>0</no_live_play><tags domain="jp"><tag lock="1">音MAD</tag><tag lock="1">キミに100パーセント</tag><tag lock="1">私的オールスター</tag><tag>シャル！</tag></tags><genre>その他</genre><user_id>93302249</user_id><user_nickname>八幡謙一</user_nickname><user_icon_url>https://secure-dcdn.cdn.nimg.jp/nicoaccount/usericon/9330/93302249.jpg?1583108512</user_icon_url></thumb></nicovideo_thumb_response>
