<?xml version="1.0" encoding="UTF-8"?>
<nicovideo_thumb_response status="ok"><thumb><video_id>sm45146965</video_id><title>三年越しに復活した奇跡のアイドルゲームをやっていく。　シャインポストBēyourアイドル　後編</title><description>これは事務所経営版ときメモだ。</description><thumbnail_url>https://nicovideo.cdn.nimg.jp/thumbnails/45146965/45146965.44524505</thumbnail_url><first_retrieve>2025-07-02T22:46:04+09:00</first_retrieve><length>12:55</length><movie_type>mp4</movie_type><size_high>1</size_high><size_low>1</size_low><view_counter>24</view_counter><comment_num>6</comment_num><mylist_counter>0</mylist_counter><last_res_body>ｵｯﾂ 音でけぇ！ ふんどしの日だな！ 知ってた ずっとやってると... ｳｯｽ</last_res_body><watch_url>https://www.nicovideo.jp/watch/sm45146965</watch_url><thumb_type>video</thumb_type><embeddable>1</embeddable><no_live_play>0</no_live_play><tags domain="jp"><tag lock="1">シャインポスト_Be_Your_アイドル！</tag><tag lock="1">シャインポスト</tag><tag lock="1">ずんだもん実況プレイ</tag><tag lock="1">四国めたん実況プレイ</tag><tag lock="1">ゲーム</tag><tag lock="1">Switch2</tag></tags><genre>ゲーム</genre><user_id>10084679</user_id><user_nickname>ゲマゲマＺ</user_nickname><user_icon_url>https://secure-dcdn.cdn.nimg.jp/nicoaccount/usericon/defaults/blank.jpg</user_icon_url></thumb></nicovideo_thumb_response>
